secp256k1_zkp/_libsecp256k1.cpython-34m.so
secp256k1_zkp/__main__.py
secp256k1_zkp/__init__.py
secp256k1_zkp-0.14.3.dist-info/WHEEL
secp256k1_zkp-0.14.3.dist-info/top_level.txt
secp256k1_zkp-0.14.3.dist-info/METADATA
secp256k1_zkp-0.14.3.dist-info/RECORD
