Metadata-Version: 2.1
Name: secp256k1-zkp
Version: 0.14.3
Summary: FFI bindings to libsecp256k1_zkp
Home-page: https://github.com/WTRMQDev/secp256k1-zkp-py
Author: Ludvig Broberg, Quirinus Quirrell
Author-email: TetsuwanAtomu@tuta.io
License: MIT
Platform: UNKNOWN
Classifier: Intended Audience :: Developers
Classifier: License :: OSI Approved :: MIT License
Classifier: Programming Language :: Python :: 2
Classifier: Programming Language :: Python :: 3
Classifier: Programming Language :: Python :: Implementation :: CPython
Classifier: Programming Language :: Python :: Implementation :: PyPy
Classifier: Topic :: Software Development :: Libraries
Classifier: Topic :: Security :: Cryptography
Requires-Dist: cffi (>=1.3.0)
